uitk/__init__.py
uitk/events.py
uitk/file_manager.py
uitk/switchboard.py
uitk/examples/__init__.py
uitk/examples/example.py
uitk/examples/example.ui
uitk/examples/icons/analyze.svg
uitk/examples/icons/autosave.svg
uitk/examples/icons/document.svg
uitk/examples/icons/font.svg
uitk/examples/icons/font_size.svg
uitk/examples/icons/info.svg
uitk/examples/icons/save.svg
uitk/examples/icons/settings.svg
uitk/examples/icons/theme.svg
uitk/handlers/ui_handler.py
uitk/icons/activity.svg
uitk/icons/add.svg
uitk/icons/analyze.svg
uitk/icons/archive.svg
uitk/icons/arrow_down.svg
uitk/icons/arrow_left.svg
uitk/icons/arrow_right.svg
uitk/icons/arrow_up.svg
uitk/icons/autosave.svg
uitk/icons/backward.svg
uitk/icons/branch.svg
uitk/icons/calendar.svg
uitk/icons/chart.svg
uitk/icons/check.svg
uitk/icons/checkbox.svg
uitk/icons/checkbox_empty.svg
uitk/icons/chevron_down.svg
uitk/icons/chevron_left.svg
uitk/icons/chevron_right.svg
uitk/icons/chevron_up.svg
uitk/icons/circle_add.svg
uitk/icons/circle_remove.svg
uitk/icons/clear.svg
uitk/icons/clipboard.svg
uitk/icons/clock.svg
uitk/icons/close.svg
uitk/icons/code.svg
uitk/icons/collapse_minus.svg
uitk/icons/columns.svg
uitk/icons/compare.svg
uitk/icons/connect.svg
uitk/icons/copy.svg
uitk/icons/crosshair.svg
uitk/icons/cut.svg
uitk/icons/dashboard.svg
uitk/icons/disconnect.svg
uitk/icons/document.svg
uitk/icons/double_chevron_left.svg
uitk/icons/double_chevron_right.svg
uitk/icons/download.svg
uitk/icons/drag.svg
uitk/icons/edit.svg
uitk/icons/error.svg
uitk/icons/expand_plus.svg
uitk/icons/export.svg
uitk/icons/eye.svg
uitk/icons/eye_off.svg
uitk/icons/file.svg
uitk/icons/filter.svg
uitk/icons/folder.svg
uitk/icons/font.svg
uitk/icons/font_size.svg
uitk/icons/forward.svg
uitk/icons/grid.svg
uitk/icons/history.svg
uitk/icons/home.svg
uitk/icons/import.svg
uitk/icons/inbox.svg
uitk/icons/info.svg
uitk/icons/layout.svg
uitk/icons/leaf.svg
uitk/icons/link.svg
uitk/icons/list.svg
uitk/icons/lock.svg
uitk/icons/mail.svg
uitk-1.0.76.dist-info/licenses/COPYING.LESSER
uitk-1.0.76.dist-info/METADATA
uitk-1.0.76.dist-info/WHEEL
uitk-1.0.76.dist-info/top_level.txt
uitk-1.0.76.dist-info/RECORD
