Metadata-Version: 2.4
Name: uitk
Version: 1.0.76
Summary: A comprehensive UI toolkit extending Qt Designer workflows with dynamic loading, custom widgets, and automatic signal-slot management.
Author-email: Ryan Simpson <m3trik@outlook.com>
License: LGPL-3.0-or-later
Project-URL: Homepage, https://github.com/m3trik/uitk
Project-URL: Repository, https://github.com/m3trik/uitk
Classifier: Programming Language :: Python :: 3
Classifier: License :: OSI Approved :: GNU Lesser General Public License v3 or later (LGPLv3+)
Classifier: Operating System :: OS Independent
Requires-Python: >=3.9
License-File: COPYING.LESSER
Requires-Dist: pythontk>=0.7.71
Dynamic: license-file
